<?xml version="1.0" encoding="utf-8" ?>
<dwsync>
<file name=".ftpquota" server="giowm1113.siteground.biz" local="133932997569044327" remote="133948696800000000" Dst="2" />
<file name=".htaccess" server="giowm1113.siteground.biz" local="133932997555715130" remote="133948696800000000" Dst="2" />
<file name=".htaccess.no_htaccess.phpupgrader" server="giowm1113.siteground.biz" local="133932997569044327" remote="133131276000000000" Dst="2" />
<file name=".htaccess.phpupgrader.cae43e47" server="giowm1113.siteground.biz" local="133932997501681862" remote="133948696800000000" Dst="2" />
<file name=".htaccess.phpupgrader.initial" server="giowm1113.siteground.biz" local="133932997484018356" remote="133948696800000000" Dst="2" />
<file name="Default.html" server="giowm1113.siteground.biz" local="133948587494527455" remote="133809178200000000" Dst="2" />
<file name="Resume-Keith-Jeter-2022-old.pdf" server="giowm1113.siteground.biz" local="133948587498238694" remote="132891948000000000" Dst="2" />
<file name="Resume-Keith-Jeter-2022-old.docx" server="giowm1113.siteground.biz" local="133948587499655993" remote="132891948000000000" Dst="2" />
<file name="Resume-Keith-Jeter-2022.docx" server="giowm1113.siteground.biz" local="133948587500771456" remote="132966288000000000" Dst="2" />
<file name="Resume-Keith-Jeter-2023-Ext.pdf" server="giowm1113.siteground.biz" local="133948587503876018" remote="133350768000000000" Dst="2" />
<file name="Resume-Keith-Jeter-2023-Ext.docx" server="giowm1113.siteground.biz" local="133948587504806125" remote="133350768000000000" Dst="2" />
<file name="Resume-Keith-Jeter-2022.pdf" server="giowm1113.siteground.biz" local="133948587507214134" remote="132966288000000000" Dst="2" />
<file name="Resume-Keith-Jeter-2023.docx" server="giowm1113.siteground.biz" local="133948587508623318" remote="133158924000000000" Dst="2" />
<file name="Resume-Keith-Jeter-2024.pdf" server="giowm1113.siteground.biz" local="133948587511941277" remote="133477740000000000" Dst="2" />
<file name="Resume-Keith-Jeter-2024.docx" server="giowm1113.siteground.biz" local="133948587512255928" remote="133477740000000000" Dst="2" />
<file name="Resume-Keith-Jeter-2023.pdf" server="giowm1113.siteground.biz" local="133948587513680040" remote="133158924000000000" Dst="2" />
<file name="Resume-Keith-Jeter.pdf" server="giowm1113.siteground.biz" local="133948587514945829" remote="132809004000000000" Dst="2" />
<file name="Resume-Keith-Jeter.docx" server="giowm1113.siteground.biz" local="133948587516220343" remote="132809004000000000" Dst="2" />
<file name="about.html" server="giowm1113.siteground.biz" local="133948587630316393" remote="133829336400000000" Dst="2" />
<file name="drawsesh.html" server="giowm1113.siteground.biz" local="133948587718735327" remote="133944296400000000" Dst="2" />
<file name="favicon.ico" server="giowm1113.siteground.biz" local="133948587720158201" remote="132725232000000000" Dst="2" />
<file name="grey-banner-5.png" server="giowm1113.siteground.biz" local="133948587718102269" remote="133933135200000000" Dst="2" />
<file name="index - Copy [2].html" server="giowm1113.siteground.biz" local="133948587992143439" remote="133724016000000000" Dst="2" />
<file name="index-2020 - Copy.html" server="giowm1113.siteground.biz" local="133948587992143439" remote="133425936000000000" Dst="2" />
<file name="index - Copy.html" server="giowm1113.siteground.biz" local="133948587992143439" remote="133663536000000000" Dst="2" />
<file name="index-2020.html" server="giowm1113.siteground.biz" local="133948587993788461" remote="132729552000000000" Dst="2" />
<file name="index-2024.html" server="giowm1113.siteground.biz" local="133948587994235384" remote="133425936000000000" Dst="2" />
<file name="index-legacy-2023.html" server="giowm1113.siteground.biz" local="133948587994669569" remote="133419888000000000" Dst="2" />
<file name="index-sample.html" server="giowm1113.siteground.biz" local="133948587995465014" remote="133940717400000000" Dst="2" />
<file name="index.html" server="giowm1113.siteground.biz" local="133948587995822755" remote="133944304200000000" Dst="2" />
<file name="index2.html" server="giowm1113.siteground.biz" local="133948587997685497" remote="133595280000000000" Dst="2" />
<file name="index3.html" server="giowm1113.siteground.biz" local="133948587998002019" remote="133798012800000000" Dst="2" />
<file name="message-center.html" server="giowm1113.siteground.biz" local="133948588126688136" remote="133916479200000000" Dst="2" />
<file name="message-center-1.html" server="giowm1113.siteground.biz" local="133948588126688136" remote="133916554800000000" Dst="2" />
<file name="newt.html" server="giowm1113.siteground.biz" local="133948588148881066" remote="133932931200000000" Dst="2" />
<file name="portfolio-details.html" server="giowm1113.siteground.biz" local="133948588490649986" remote="132819372000000000" Dst="2" />
<file name="portfolio.html" server="giowm1113.siteground.biz" local="133948588493182660" remote="132819372000000000" Dst="2" />
<file name="test - Copy.html" server="giowm1113.siteground.biz" local="133948588500889678" remote="133459596000000000" Dst="2" />
<file name="test.html" server="giowm1113.siteground.biz" local="133948588501362920" remote="133458732000000000" Dst="2" />
<file name="test2.html" server="giowm1113.siteground.biz" local="133948588501873956" remote="133476012000000000" Dst="2" />
<file name="webawesome.html" server="giowm1113.siteground.biz" local="133948588547915652" remote="133902927000000000" Dst="2" />
</dwsync>